wpapi/__init__.py
wpapi/core.py
wpapi/posts.py
wpapi/sync.py
wpapi/utils.py
wpapi-0.0.2.dist-info/LICENSE.txt
wpapi-0.0.2.dist-info/METADATA
wpapi-0.0.2.dist-info/WHEEL
wpapi-0.0.2.dist-info/top_level.txt
wpapi-0.0.2.dist-info/RECORD
