Metadata-Version: 2.1
Name: wpapi
Version: 0.0.2
Summary: Python WordPress API
Home-page: https://github.com/quantology/wpapi
Author: Michael Tartre
Author-email: mt@quantology.org
License: Community Clause BSD-3
Platform: UNKNOWN
Classifier: Programming Language :: Python :: 3 :: Only
Classifier: Programming Language :: Python :: 3.3
Classifier: Programming Language :: Python :: 3.4
Classifier: Programming Language :: Python :: 3.5
Classifier: Programming Language :: Python :: 3.6
Classifier: Programming Language :: Python :: 3.7
Classifier: Programming Language :: Python :: 3.8
Classifier: Programming Language :: Python :: 3.9
Classifier: Programming Language :: Python :: 3.10
Classifier: Intended Audience :: Developers
Classifier: Topic :: Software Development :: Libraries
Classifier: Topic :: Utilities
Classifier: Development Status :: 3 - Alpha
Classifier: Operating System :: OS Independent
Requires-Dist: mistune
Requires-Dist: frontmatter
Requires-Dist: requests
